pyculiarity_plus/__init__.py
pyculiarity_plus/detect_anoms.py
pyculiarity_plus/detect_ts.py
pyculiarity_plus/seasonal/__init__.py
pyculiarity_plus/seasonal/periodogram.py
pyculiarity_plus/seasonal/seasonal.py
pyculiarity_plus/seasonal/trend.py
pyculiarity_plus/seasonal/version.py
pyculiarity_plus-0.2.0.dist-info/METADATA
pyculiarity_plus-0.2.0.dist-info/WHEEL
pyculiarity_plus-0.2.0.dist-info/top_level.txt
pyculiarity_plus-0.2.0.dist-info/RECORD
